[
  {
    "name": "Recept s ingrediencemi",
    "description": "Příprava trvá 60 minut a počet porcí je 5. Recept má 3 ingredience.",
    "imageId": "",
    "preparationLength": 15,
    "finalAmount": 5,
    "ingredients": [
      {
        "id": "1",
        "amount": 50,
        "units": "unit1"
      },
      {
        "id": "2",
        "amount": 200,
        "units": "unit2"
      },
      {
        "id": "5",
        "amount": 500,
        "units": "unit5"
      }
    ],
    "_id": "b2c89236fd16523d"
  },
  {
    "name": "jídlo",
    "description": "připrav jídlo",
    "imageId": "",
    "preparationLength": 1,
    "finalAmount": 1,
    "ingredients": [
      {
        "id": "",
        "amount": 10,
        "units": "g"
      }
    ],
    "_id": "4426d58b81734da2"
  },
  {
    "name": "jirka",
    "description": "jirkův recept",
    "imageId": "",
    "preparationLength": 60,
    "finalAmount": 1,
    "ingredients": [
      {
        "id": "",
        "amount": 10,
        "units": "g"
      }
    ],
    "_id": "5a3bb70f4f9841fd"
  },
  {
    "name": "já to testuji",
    "description": "tady je ten recept",
    "imageId": "",
    "preparationLength": 60,
    "finalAmount": 1,
    "ingredients": [
      {
        "id": "",
        "amount": 10,
        "units": "g"
      }
    ],
    "_id": "b9e8d4e5a0c6735d"
  },
  {
    "name": "halééjkkhaskjhs",
    "description": "sA ,SHAhs.A H",
    "imageId": "",
    "preparationLength": 60,
    "finalAmount": 1,
    "ingredients": [
      {
        "id": "",
        "amount": 10,
        "units": "g"
      }
    ],
    "_id": "75b90c86e71c2e3f"
  },
  {
    "name": "halééjkkhaskjhsDSDSDS",
    "description": "sA ,SHAhs.A HDSDSDSD",
    "imageId": "",
    "preparationLength": 60,
    "finalAmount": 1,
    "ingredients": [
      {
        "id": "",
        "amount": 10,
        "units": "g"
      }
    ],
    "_id": "aaeb8556a7c6af95"
  },
  {
    "name": "SVÍČKOVÁ NA HOUBÁCH",
    "description": "V mase na několika místech úzkým nožem prořízneme kapsy, do kterých vsuneme namražené špalíčky špeku. Maso důkladně osolíme a opepříme čerstvě mletým pepřem ze všech stran. V kastrolu na vyšším ohni rozpálíme sádlo a maso na něm opečeme ze všech stran dohněda. Maso vyndáme na čistý talíř.\n3Snížíme oheň pod polovinu, do kastrolu přidáme máslo a případně špek, který zbyl ze špikování masa. Přidáme mrkev, celer a petržel a za častého míchání je orestujeme dozlatova. Přidáme cibuli a orestujeme ji dozlatova. Přidáme jablko a i to orestujeme dozlatova. Často mícháme.\n4Přidáme cukr, zamícháme a necháme ho rozpustit. Přidáme hořčici a pytlíček koření. Promícháme. Přilijeme ocet a necháme ho zcela vyvařit, takže na dně kastrolu zbude opět jen tuk. Žádná tekutina. Zalijeme vínem, které necháme odvařit na polovinu objemu. Vložíme maso a zalijeme ho horkou vodou, tak aby bylo téměř ponořené. Přidáme 1 lžičku soli.",
    "imageId": "",
    "preparationLength": 60,
    "finalAmount": 1,
    "ingredients": [
      {
        "id": "",
        "amount": 10,
        "units": "g"
      }
    ],
    "_id": "77280d7be1c98c3c"
  },
  {
    "name": "Houby na houbách",
    "description": "Přidáme cukr, zamícháme a necháme ho rozpustit. Přidáme hořčici a pytlíček koření. Promícháme. Přilijeme ocet a necháme ho zcela vyvařit, takže na dně kastrolu zbude opět jen tuk. Žádná tekutina. Zalijeme vínem, které necháme odvařit na polovinu objemu. Vložíme maso a zalijeme ho horkou vodou, tak aby bylo téměř ponořené. Přidáme 1 lžičku soli.\n5Přivedeme k varu, stáhneme oheň na minimum, přiklopíme poklicí a necháme pomalu dusit 2,5 hodiny nebo než bude maso zcela měkké. Poté vyjmeme sáček s kořením a maso, které dáme stranou na teplé místo.\n6Na jemném struhadle nastrouháme žlutou část kůry z poloviny omytého citronu a přidáme ji do omáčky společně",
    "imageId": "",
    "preparationLength": 60,
    "finalAmount": 1,
    "ingredients": [
      {
        "id": "",
        "amount": 10,
        "units": "g"
      }
    ],
    "_id": "26c5cf41bccd5008"
  },
  {
    "name": "Nový recept",
    "description": "Být dobrým manažerem je úloha poměrně složitá. Pro jednoduchost si tuto úlohu dekomponujeme na dílčí činnosti, které manažer během své práce v týmu vykonává. Existuje mnoho možností, jak jednotlivé manažerské dovednosti rozvíjet. Co je však pro úspěšný rozvoj manažera nezbytné, je umět jednotlivé dovednosti v rámci jedné osobnosti vzájemně integrovat. Pokud například získáte zkušenosti v oblasti hodnocení a motivace, přemýšlejte, jak tyto zkušenosti propojit se zkušenostmi z oblastí ostatních dovedností a naopak.",
    "imageId": "",
    "preparationLength": 60,
    "finalAmount": 1,
    "ingredients": [
      {
        "id": "",
        "amount": 10,
        "units": "g"
      }
    ],
    "_id": "2777490712336c90"
  },
  {
    "name": "Jirka test",
    "description": "tady",
    "imageId": "",
    "preparationLength": 60,
    "finalAmount": 1,
    "ingredients": [
      {
        "id": "",
        "amount": 10,
        "units": "g"
      }
    ],
    "_id": "d1267c70a24441a1"
  },
  {
    "name": "Burger",
    "description": "Výroba Houska atd",
    "imageId": "",
    "preparationLength": 10,
    "finalAmount": 1,
    "ingredients": [
      {
        "id": "",
        "amount": 10,
        "units": "g"
      }
    ],
    "_id": "6c32ab295c70fb07"
  },
  {
    "name": "recept recept",
    "description": "jojojojo",
    "imageId": "",
    "preparationLength": 60,
    "finalAmount": 1,
    "ingredients": [
      {
        "id": "",
        "amount": 10,
        "units": "g"
      }
    ],
    "_id": "6acf5d36ec567057"
  },
  {
    "name": "e nedělní polévk",
    "description": "ová zelňačka, jejíž příprava zabere 30 minut, sice může posloužit jako všednodenní snadná večeře, ale mnohem víc jí bude slušet role nedělní polévky. Aniž by přesun na neděli jakkoli zvýšil její pracnost.\n\nNedělní polévku z ní dělá jen a pouze to, že jinak obyčejná polévka typu zelňačka nabere během vaření trochu jinou, nezvyklou podobu.\n\nUrčitě si říkáte, jak se to stane, že se obyčejná zelňačka na talíři takhle zvrtne. Stane se to tak, že ",
    "imageId": "",
    "preparationLength": 60,
    "finalAmount": 1,
    "ingredients": [
      {
        "id": "",
        "amount": 10,
        "units": "g"
      }
    ],
    "_id": "fd29ae34e53321d2"
  },
  {
    "name": "nn",
    "description": "bbv",
    "imageId": "",
    "preparationLength": 60,
    "finalAmount": 1,
    "ingredients": [
      {
        "id": "",
        "amount": 10,
        "units": "g"
      }
    ],
    "_id": "49c09845d7c36d46"
  },
  {
    "name": "jfgjfjfg",
    "description": "gfjfjvcchfddhd",
    "imageId": "",
    "preparationLength": 60,
    "finalAmount": 1,
    "ingredients": [
      {
        "id": "",
        "amount": 10,
        "units": "g"
      }
    ],
    "_id": "2c409b12709b318d"
  },
  {
    "name": "cscsc",
    "description": "dsgsdgsdg",
    "imageId": "",
    "preparationLength": 60,
    "finalAmount": 1,
    "ingredients": [
      {
        "id": "",
        "amount": 10,
        "units": "g"
      }
    ],
    "_id": "e2d321aeaff3b421"
  },
  {
    "name": "\\ycy\\c",
    "description": "cxyvxyvxyv",
    "imageId": "",
    "preparationLength": 60,
    "finalAmount": 1,
    "ingredients": [
      {
        "id": "",
        "amount": 10,
        "units": "g"
      }
    ],
    "_id": "1585eed185552a8e"
  },
  {
    "name": "fdfs",
    "description": "sdfsdgdsgs",
    "imageId": "",
    "preparationLength": 60,
    "finalAmount": 1,
    "ingredients": [
      {
        "id": "",
        "amount": 10,
        "units": "g"
      }
    ],
    "_id": "5983d5fd13561367"
  },
  {
    "name": "cxvcv",
    "description": "xsdsdsdsdsd",
    "imageId": "",
    "preparationLength": 60,
    "finalAmount": 1,
    "ingredients": [
      {
        "id": "",
        "amount": 10,
        "units": "g"
      }
    ],
    "_id": "0b1d7e7f329171c8"
  },
  {
    "name": "bb",
    "description": "123",
    "imageId": "",
    "preparationLength": 60,
    "finalAmount": 1,
    "ingredients": [
      {
        "id": "",
        "amount": 10,
        "units": "g"
      }
    ],
    "_id": "774db44cf6ace249"
  },
  {
    "name": "hbn",
    "description": "nm    bbbb",
    "imageId": "",
    "preparationLength": 60,
    "finalAmount": 1,
    "ingredients": [
      {
        "id": "",
        "amount": 10,
        "units": "g"
      }
    ],
    "_id": "425c9ea2f60f134e"
  },
  {
    "name": "",
    "description": "",
    "imageId": "",
    "preparationLength": 60,
    "finalAmount": 1,
    "ingredients": [
      {
        "id": "",
        "amount": 10,
        "units": "g"
      }
    ],
    "_id": "a095d9d781c1043b"
  },
  {
    "name": "hgh",
    "description": "ghgh",
    "imageId": "",
    "preparationLength": 60,
    "finalAmount": 1,
    "ingredients": [
      {
        "id": "",
        "amount": 10,
        "units": "g"
      }
    ],
    "_id": "5fdf33c88328a5f8"
  },
  {
    "name": "trrrrrrrrrrrrrrrrrrrrrrrr",
    "description": "sdsadd",
    "imageId": "",
    "preparationLength": 10,
    "finalAmount": 2,
    "ingredients": [
      {
        "id": "",
        "amount": 10,
        "units": "g"
      }
    ],
    "_id": "80b64d7ab7c62900"
  },
  {
    "name": "trrrrrrrrrrrrrrrrrrrrrrrr",
    "description": "sdsadd",
    "imageId": "",
    "preparationLength": 10,
    "finalAmount": 2,
    "ingredients": [
      {
        "id": "",
        "amount": 10,
        "units": "g"
      }
    ],
    "_id": "30ae2532316508ef"
  },
  {
    "name": "1",
    "description": "2",
    "imageId": "",
    "preparationLength": 3,
    "finalAmount": 4,
    "ingredients": [
      {
        "id": "",
        "amount": 10,
        "units": "g"
      }
    ],
    "_id": "1eb1775cd28a0484"
  },
  {
    "name": "test",
    "description": "12",
    "imageId": "",
    "preparationLength": 1,
    "finalAmount": 1,
    "ingredients": [
      {
        "id": "",
        "amount": 10,
        "units": "g"
      }
    ],
    "_id": "c2b85329e5506e98"
  },
  {
    "name": "h",
    "description": "k",
    "imageId": "",
    "preparationLength": 1,
    "finalAmount": 1,
    "ingredients": [
      {
        "id": "",
        "amount": 10,
        "units": "g"
      }
    ],
    "_id": "b5384ecdaf425afa"
  },
  {
    "name": "f",
    "description": "d",
    "imageId": "",
    "preparationLength": 1,
    "finalAmount": 1,
    "ingredients": [
      {
        "id": "",
        "amount": 10,
        "units": "g"
      }
    ],
    "_id": "d746b6979535aee1"
  },
  {
    "name": "s",
    "description": "f",
    "imageId": "",
    "preparationLength": 1,
    "finalAmount": 1,
    "ingredients": [
      {
        "id": "",
        "amount": 10,
        "units": "g"
      }
    ],
    "_id": "181414922ad857c2"
  },
  {
    "name": "f",
    "description": "g",
    "imageId": "",
    "preparationLength": 1,
    "finalAmount": 1,
    "ingredients": [
      {
        "id": "",
        "amount": 10,
        "units": "g"
      }
    ],
    "_id": "fafe2cfde5ddf9ef"
  },
  {
    "name": "m",
    "description": "h",
    "imageId": "",
    "preparationLength": 1,
    "finalAmount": 5,
    "ingredients": [
      {
        "id": "",
        "amount": 10,
        "units": "g"
      }
    ],
    "_id": "c1d382bd4cba1abf"
  },
  {
    "name": "u",
    "description": "ž",
    "imageId": "",
    "preparationLength": 1,
    "finalAmount": 1,
    "ingredients": [
      {
        "id": "",
        "amount": 10,
        "units": "g"
      }
    ],
    "_id": "bcc0f586cf653401"
  },
  {
    "name": "l",
    "description": "k",
    "imageId": "",
    "preparationLength": 1,
    "finalAmount": 1,
    "ingredients": [
      {
        "id": "",
        "amount": 10,
        "units": "g"
      }
    ],
    "_id": "1d1928b1c3bd31c3"
  },
  {
    "name": "o",
    "description": "i",
    "imageId": "",
    "preparationLength": 1,
    "finalAmount": 1,
    "ingredients": [
      {
        "id": "",
        "amount": 10,
        "units": "g"
      }
    ],
    "_id": "fb2e13917f4ae374"
  },
  {
    "name": "k",
    "description": "ů",
    "imageId": "",
    "preparationLength": 1,
    "finalAmount": 1,
    "ingredients": [
      {
        "id": "",
        "amount": 10,
        "units": "g"
      }
    ],
    "_id": "6eb17d402aada3b0"
  },
  {
    "name": "u",
    "description": "o",
    "imageId": "",
    "preparationLength": 1,
    "finalAmount": 1,
    "ingredients": [
      {
        "id": "",
        "amount": 10,
        "units": "g"
      }
    ],
    "_id": "35fa5960749d42da"
  },
  {
    "name": "d",
    "description": "s",
    "imageId": "",
    "preparationLength": 1,
    "finalAmount": 1,
    "ingredients": [
      {
        "id": "",
        "amount": 10,
        "units": "g"
      }
    ],
    "_id": "c527d7ca1cfa46f1"
  },
  {
    "name": "h",
    "description": "k",
    "imageId": "",
    "preparationLength": 1,
    "finalAmount": 1,
    "ingredients": [
      {
        "id": "",
        "amount": 10,
        "units": "g"
      }
    ],
    "_id": "3515276734b741fb"
  },
  {
    "name": "k",
    "description": "g",
    "imageId": "",
    "preparationLength": 1,
    "finalAmount": 1,
    "ingredients": [
      {
        "id": "",
        "amount": 10,
        "units": "g"
      }
    ],
    "_id": "1287e71a9bf6a306"
  },
  {
    "name": "h",
    "description": "x",
    "imageId": "",
    "preparationLength": 1,
    "finalAmount": 1,
    "ingredients": [
      {
        "id": "",
        "amount": 10,
        "units": "g"
      }
    ],
    "_id": "3e36d23352abb323"
  },
  {
    "name": "n",
    "description": "f",
    "imageId": "",
    "preparationLength": 1,
    "finalAmount": 1,
    "ingredients": [
      {
        "id": "",
        "amount": 10,
        "units": "g"
      }
    ],
    "_id": "3ebf0199c12b0f60"
  },
  {
    "name": "j",
    "description": "h",
    "imageId": "",
    "preparationLength": 1,
    "finalAmount": 1,
    "ingredients": [
      {
        "id": "",
        "amount": 10,
        "units": "g"
      }
    ],
    "_id": "566e4006c7ad73ec"
  },
  {
    "name": "k",
    "description": "j",
    "imageId": "",
    "preparationLength": 1,
    "finalAmount": 1,
    "ingredients": [
      {
        "id": "",
        "amount": 10,
        "units": "g"
      }
    ],
    "_id": "d1107b3702bffed2"
  },
  {
    "name": "t",
    "description": "z",
    "imageId": "",
    "preparationLength": 1,
    "finalAmount": 1,
    "ingredients": [
      {
        "id": "",
        "amount": 10,
        "units": "g"
      }
    ],
    "_id": "960d6db00f509fb2"
  },
  {
    "name": "m",
    "description": "b",
    "imageId": "",
    "preparationLength": 1,
    "finalAmount": 1,
    "ingredients": [
      {
        "id": "",
        "amount": 10,
        "units": "g"
      }
    ],
    "_id": "bc236773808ad292"
  },
  {
    "name": "b",
    "description": "m",
    "imageId": "",
    "preparationLength": 1,
    "finalAmount": 1,
    "ingredients": [
      {
        "id": "",
        "amount": 10,
        "units": "g"
      }
    ],
    "_id": "2d8632f42369a4e7"
  },
  {
    "name": "m",
    "description": "t",
    "imageId": "",
    "preparationLength": 1,
    "finalAmount": 1,
    "ingredients": [
      {
        "id": "",
        "amount": 10,
        "units": "g"
      }
    ],
    "_id": "e1e2ab09d3746acc"
  },
  {
    "name": "1",
    "description": "2",
    "imageId": "",
    "preparationLength": 1,
    "finalAmount": 1,
    "ingredients": [
      {
        "id": "",
        "amount": 10,
        "units": "g"
      }
    ],
    "_id": "079d6051f8d1919c"
  },
  {
    "name": "v",
    "description": "c",
    "imageId": "",
    "preparationLength": 1,
    "finalAmount": 1,
    "ingredients": [
      {
        "id": "",
        "amount": 10,
        "units": "g"
      }
    ],
    "_id": "2f05c4dd6bb9f2d1"
  },
  {
    "name": "1",
    "description": "2",
    "imageId": "",
    "preparationLength": 1,
    "finalAmount": 1,
    "ingredients": [
      {
        "id": "",
        "amount": 10,
        "units": "g"
      }
    ],
    "_id": "262d738c01b55d71"
  },
  {
    "name": "j",
    "description": "h",
    "imageId": "",
    "preparationLength": 1,
    "finalAmount": 1,
    "ingredients": [
      {
        "id": "",
        "amount": 10,
        "units": "g"
      }
    ],
    "_id": "14a9dd7e2cac2d29"
  },
  {
    "name": "l",
    "description": "j",
    "imageId": "",
    "preparationLength": 1,
    "finalAmount": 1,
    "ingredients": [
      {
        "id": "",
        "amount": 10,
        "units": "g"
      }
    ],
    "_id": "7239c0b3d3edcfcd"
  },
  {
    "name": "g",
    "description": "h",
    "imageId": "",
    "preparationLength": 1,
    "finalAmount": 1,
    "ingredients": [
      {
        "id": "",
        "amount": 10,
        "units": "g"
      }
    ],
    "_id": "08ae8700dd7f4feb"
  },
  {
    "name": "m",
    "description": "v",
    "imageId": "",
    "preparationLength": 1,
    "finalAmount": 1,
    "ingredients": [
      {
        "id": "",
        "amount": 10,
        "units": "g"
      }
    ],
    "_id": "1317424dbb449051"
  },
  {
    "name": " d",
    "description": "s",
    "imageId": "",
    "preparationLength": 1,
    "finalAmount": 1,
    "ingredients": [
      {
        "id": "",
        "amount": 10,
        "units": "g"
      }
    ],
    "_id": "992039051502fe26"
  },
  {
    "name": "g",
    "description": "n",
    "imageId": "",
    "preparationLength": 1,
    "finalAmount": 1,
    "ingredients": [
      {
        "id": "",
        "amount": 10,
        "units": "g"
      }
    ],
    "_id": "efcfb9e44520893f"
  },
  {
    "name": "l",
    "description": "g",
    "imageId": "",
    "preparationLength": 1,
    "finalAmount": 1,
    "ingredients": [
      {
        "id": "",
        "amount": 10,
        "units": "g"
      }
    ],
    "_id": "d2220b857bfe44c4"
  },
  {
    "name": "c",
    "description": "l",
    "imageId": "",
    "preparationLength": 1,
    "finalAmount": 1,
    "ingredients": [
      {
        "id": "",
        "amount": 10,
        "units": "g"
      }
    ],
    "_id": "6341392c2438c4a4"
  },
  {
    "name": "b",
    "description": "v",
    "imageId": "",
    "preparationLength": 1,
    "finalAmount": 1,
    "ingredients": [
      {
        "id": "",
        "amount": 10,
        "units": "g"
      }
    ],
    "_id": "44e93e8b3d957320"
  },
  {
    "name": "h",
    "description": "g",
    "imageId": "",
    "preparationLength": 1,
    "finalAmount": 1,
    "ingredients": [
      {
        "id": "",
        "amount": 10,
        "units": "g"
      }
    ],
    "_id": "fd43cfc4b10c9978"
  },
  {
    "name": "j on clicking submit button",
    "description": "Enable Disable Submit Button Based on Validation\nby Vincy. Last modified on July 12th, 2022.\nNow we are going to see about how to enable or disable form submit button based on the form validation result. In a previous example, we have seen form validation using PHP on clicking submit button.\n\nWe have an example with an HTML form with disabled submit button. And then, we are enabling it by validating form fields using jQuery.",
    "imageId": "",
    "preparationLength": 1,
    "finalAmount": 1,
    "ingredients": [
      {
        "id": "",
        "amount": 10,
        "units": "g"
      }
    ],
    "_id": "ff0d2dc77886a44e"
  }
]